spi_master.v
module spi_master (
    input wire clk,     // Системная тактовая частота (50 МГц)
    input wire rst_n,   // Сброс (активный, когда 0/"активный низкий")
    output reg sclk,    // Тактовый сигнал SPI
    output reg cs_n,    // Chip Select, выбор АЦП (активный 0)
    output reg mosi,    // Данные от мастера
    input wire miso,    // Данные от АЦП
    output reg [11:0] adc_data  // Принятые 12 бит данных
);

reg [3:0] bit_cnt;  // Счётчик, сколько битов данных было передано/принято
reg [11:0] data_buf;    // Буфер, для приёма данных
reg spi_active;     // Активна ли передача данных по SPI?

// Основной always-блок
// Выполняется при: по переднему фронту тактового сигнала / по спаду сигнала сброса
always @(posedge clk or negedge rst_n) begin

    // Условие сброса
    if (!rst_n) begin   // Сигнал сброса активен rst_n = 0
        cs_n <= 1;      // Сброс сигнала Chip Select.
        sclk <= 0;      // Сюрос тактового сигнала
        bit_cnt <= 0;   // Обнуляем счетчик переданных битов
        spi_active <= 0;    // Остановка передачи данных

    end else begin      // Сигнал сброса неактивен rst_n = 1

        if (spi_active) begin   // Активна ли передача данных?
            sclk <= ~sclk; // Генерируем SPI SCLK

            // Чтение данных по MISO.
            if (sclk) begin     // Выполнение на положительном/отрицательном фронте SCLK
                if (bit_cnt < 12) begin
                    data_buf <= {data_buf[10:0], miso};     // data_buf[10:0] - сдвиг данных влево на 1 бит, miso - принимаем следующий бит
                    bit_cnt <= bit_cnt + 1;

                end else begin      // 12 битов уже принято
                    adc_data <= data_buf;       // Запись результата из буфера
                    cs_n <= 1;                  // Отключение АЦП (Chip Select)
                    spi_active <= 0;            // Завершение передачи
                end
            end
        end
    end
end

// Задача запуска SPI
task start_spi;     // Процедура для вызова запуска SPI
    begin
        cs_n <= 0;
        bit_cnt <= 0;
        spi_active <= 1;
    end
endtask

endmodule

Verilog Related Features/spi_master_tb.v
`timescale 1ns / 1ps

module spi_master_tb;

  // Локальные сигналы
  reg clk;
  reg rst_n;
  wire sclk;
  wire cs_n;
  wire mosi;
  reg miso;
  wire [11:0] adc_data;

  // Экземпляр (Unit Under Test) модуля spi_master
  spi_master uut (
    .clk(clk),
    .rst_n(rst_n),
    .sclk(sclk),
    .cs_n(cs_n),
    .mosi(mosi),
    .miso(miso),
    .adc_data(adc_data)
  );

  // Генерация тактового сигнала: 50 МГц => период 20 нс
  always #10 clk = ~clk;

  // Для записи в VCD-файл (просмотр в GTKWave)
  initial begin
    $dumpfile("dump.vcd");   // Имя файла с "волнами"
    $dumpvars(0, spi_master_tb); // Записываем все сигналы уровня 0 (весь тестбенч)
  end

  initial begin
    // Инициализация
    clk = 0;
    rst_n = 0;
    miso = 0;

    // Держим сброс немного
    #50;
    rst_n = 1;
    #20;

    // Запускаем SPI
    uut.start_spi();

    // Эмулируем приход 12 бит на MISO
    // Допустим, хотим "передать" 12'b101010101010
    // Но можно и случайно: miso = $random % 2;
    repeat (12) begin
      miso = 1;  // здесь можно чередовать 0/1
      #20;
      miso = 0;
      #20;
    end

    // Немного ждём и завершаем
    #200;
    $display("ADC Data = %b", adc_data);
    $finish;
  end

endmodule

Verilog Related Features/dump.vcd
$date
	Tue Apr 08 13:10:19 2025
$end
$version
	Icarus Verilog
$end
$timescale
	1ps
$end
$scope module spi_master_tb $end
$var wire 1 ! sclk $end
$var wire 1 " mosi $end
$var wire 1 # cs_n $end
$var wire 12 $ adc_data [11:0] $end
$var reg 1 % clk $end
$var reg 1 & miso $end
$var reg 1 ' rst_n $end
$scope module uut $end
$var wire 1 % clk $end
$var wire 1 & miso $end
$var wire 1 ' rst_n $end
$var reg 12 ( adc_data [11:0] $end
$var reg 4 ) bit_cnt [3:0] $end
$var reg 1 # cs_n $end
$var reg 12 * data_buf [11:0] $end
$var reg 1 " mosi $end
$var reg 1 ! sclk $end
$var reg 1 + spi_active $end
$scope task start_spi $end
$upscope $end
$upscope $end
$upscope $end
$enddefinitions $end
$comment Show the parameter values. $end
$dumpall
$end
#0
$dumpvars
0+
bx *
b0 )
bx (
0'
0&
0%
bx $
1#
x"
0!
$end
#10000
1%
#20000
0%
#30000
1%
#40000
0%
#50000
1%
1'
#60000
0%
#70000
1+
0#
1%
1&
#80000
0%
#90000
1!
1%
0&
#100000
0%
#110000
b1 )
bx1 *
0!
1%
1&
#120000
0%
#130000
1!
1%
0&
#140000
0%
#150000
b10 )
bx11 *
0!
1%
1&
#160000
0%
#170000
1!
1%
0&
#180000
0%
#190000
b11 )
bx111 *
0!
1%
1&
#200000
0%
#210000
1!
1%
0&
#220000
0%
#230000
b100 )
bx1111 *
0!
1%
1&
#240000
0%
#250000
1!
1%
0&
#260000
0%
#270000
b101 )
bx11111 *
0!
1%
1&
#280000
0%
#290000
1!
1%
0&
#300000
0%
#310000
b110 )
bx111111 *
0!
1%
1&
#320000
0%
#330000
1!
1%
0&
#340000
0%
#350000
b111 )
bx1111111 *
0!
1%
1&
#360000
0%
#370000
1!
1%
0&
#380000
0%
#390000
b1000 )
bx11111111 *
0!
1%
1&
#400000
0%
#410000
1!
1%
0&
#420000
0%
#430000
b1001 )
bx111111111 *
0!
1%
1&
#440000
0%
#450000
1!
1%
0&
#460000
0%
#470000
b1010 )
bx1111111111 *
0!
1%
1&
#480000
0%
#490000
1!
1%
0&
#500000
0%
#510000
b1011 )
bx11111111111 *
0!
1%
1&
#520000
0%
#530000
1!
1%
0&
#540000
0%
#550000
b1100 )
b111111111110 *
0!
1%
#560000
0%
#570000
1!
1%
#580000
0%
#590000
0+
1#
b111111111110 $
b111111111110 (
0!
1%
