Verilog Related Features/spi_master_16bit.v
module spi_master_16bit (
    input wire clk,             // Системная тактовая частота (50 МГц)
    input wire rst_n,           // Сброс (активный низкий)
    input wire start,           // Новый управляющий сигнал: запуск передачи
    output reg sclk,            // Тактовый сигнал SPI
    output reg cs_n,            // Chip Select (активный низкий)
    output reg mosi,            // Для расширения (не используется здесь)
    input wire miso,            // Данные от АЦП
    output reg [15:0] adc_data  // Принятые 16 бит данных
);

reg [3:0] bit_cnt;              // Счётчик принятых бит
reg [15:0] data_buf;           // Буфер приёма
reg spi_active;                // Флаг активности SPI

always @(posedge clk or negedge rst_n) begin
    if (!rst_n) begin
        cs_n <= 1;
        sclk <= 0;
        bit_cnt <= 0;
        spi_active <= 0;
        adc_data <= 0;
    end else begin
        if (start && !spi_active) begin
            cs_n <= 0;
            bit_cnt <= 0;
            spi_active <= 1;
            sclk <= 0;
        end else if (spi_active) begin
            sclk <= ~sclk;

            if (sclk) begin
                if (bit_cnt < 16) begin
                    data_buf <= {data_buf[14:0], miso};
                    bit_cnt <= bit_cnt + 1;
                end else begin
                    adc_data <= data_buf;
                    cs_n <= 1;
                    spi_active <= 0;
                end
            end
        end
    end
end

endmodule

Verilog Related Features/spi_master_tb_16bit.v
`timescale 1ns / 1ps

module spi_master_tb_16bit;

  // Сигналы
  reg clk;
  reg rst_n;
  reg start;
  wire sclk;
  wire cs_n;
  wire mosi;
  reg miso;
  wire [15:0] adc_data;

  reg [15:0] input_data;
  integer i;

  // Подключение модуля
  spi_master_16bit uut (
    .clk(clk),
    .rst_n(rst_n),
    .start(start),
    .sclk(sclk),
    .cs_n(cs_n),
    .mosi(mosi),
    .miso(miso),
    .adc_data(adc_data)
  );

  // Генерация тактового сигнала
  always #10 clk = ~clk;

  // Инициализация
  initial begin
    $dumpfile("dump.vcd");
    $dumpvars(0, spi_master_tb_16bit);
  end

  initial begin
    clk = 0;
    rst_n = 0;
    start = 0;
    miso = 0;
    input_data = 16'b1010101010101010;

    // Сброс
    #50;
    rst_n = 1;
    #20;

    // Запуск SPI-передачи
    start = 1;
    #20;
    start = 0;

    // Подача данных на MISO синхронно со SPI тактами
    for (i = 15; i >= 0; i = i - 1) begin
      @(negedge sclk);
      miso = input_data[i];
    end

    // Ожидание завершения
    #200;
    $display("ADC Data = %b", adc_data);
    $finish;
  end

endmodule

Verilog Related Features/dump.vcd
$date
	Wed Apr 23 16:07:32 2025
$end
$version
	Icarus Verilog
$end
$timescale
	1ps
$end
$scope module spi_master_tb_16bit $end
$var wire 1 ! sclk $end
$var wire 1 " mosi $end
$var wire 1 # cs_n $end
$var wire 16 $ adc_data [15:0] $end
$var reg 1 % clk $end
$var reg 16 & input_data [15:0] $end
$var reg 1 ' miso $end
$var reg 1 ( rst_n $end
$var reg 1 ) start $end
$var integer 32 * i [31:0] $end
$scope module uut $end
$var wire 1 % clk $end
$var wire 1 ' miso $end
$var wire 1 ( rst_n $end
$var wire 1 ) start $end
$var reg 16 + adc_data [15:0] $end
$var reg 4 , bit_cnt [3:0] $end
$var reg 1 # cs_n $end
$var reg 16 - data_buf [15:0] $end
$var reg 1 " mosi $end
$var reg 1 ! sclk $end
$var reg 1 . spi_active $end
$upscope $end
$upscope $end
$enddefinitions $end
$comment Show the parameter values. $end
$dumpall
$end
#0
$dumpvars
0.
bx -
b0 ,
b0 +
bx *
0)
0(
0'
b1010101010101010 &
0%
b0 $
1#
x"
0!
$end
#10000
1%
#20000
0%
#30000
1%
#40000
0%
#50000
1%
1(
#60000
0%
#70000
1.
0#
1%
1)
#80000
0%
#90000
1!
1%
b1111 *
0)
#100000
0%
#110000
b1110 *
1'
b1 ,
bx0 -
0!
1%
#120000
0%
#130000
1!
1%
#140000
0%
#150000
b1101 *
0'
b10 ,
bx01 -
0!
1%
#160000
0%
#170000
1!
1%
#180000
0%
#190000
b1100 *
1'
b11 ,
bx010 -
0!
1%
#200000
0%
#210000
1!
1%
#220000
0%
#230000
b1011 *
0'
b100 ,
bx0101 -
0!
1%
#240000
0%
#250000
1!
1%
#260000
0%
#270000
b1010 *
1'
b101 ,
bx01010 -
0!
1%
#280000
0%
#290000
1!
1%
#300000
0%
#310000
b1001 *
0'
b110 ,
bx010101 -
0!
1%
#320000
0%
#330000
1!
1%
#340000
0%
#350000
b1000 *
1'
b111 ,
bx0101010 -
0!
1%
#360000
0%
#370000
1!
1%
#380000
0%
#390000
b111 *
0'
b1000 ,
bx01010101 -
0!
1%
#400000
0%
#410000
1!
1%
#420000
0%
#430000
b110 *
1'
b1001 ,
bx010101010 -
0!
1%
#440000
0%
#450000
1!
1%
#460000
0%
#470000
b101 *
0'
b1010 ,
bx0101010101 -
0!
1%
#480000
0%
#490000
1!
1%
#500000
0%
#510000
b100 *
1'
b1011 ,
bx01010101010 -
0!
1%
#520000
0%
#530000
1!
1%
#540000
0%
#550000
b11 *
0'
b1100 ,
bx010101010101 -
0!
1%
#560000
0%
#570000
1!
1%
#580000
0%
#590000
b10 *
1'
b1101 ,
bx0101010101010 -
0!
1%
#600000
0%
#610000
1!
1%
#620000
0%
#630000
b1 *
0'
b1110 ,
bx01010101010101 -
0!
1%
#640000
0%
#650000
1!
1%
#660000
0%
#670000
b0 *
1'
b1111 ,
bx010101010101010 -
0!
1%
#680000
0%
#690000
1!
1%
#700000
0%
#710000
b11111111111111111111111111111111 *
0'
b0 ,
b101010101010101 -
0!
1%
#720000
0%
#730000
1!
1%
#740000
0%
#750000
b1 ,
b1010101010101010 -
0!
1%
#760000
0%
#770000
1!
1%
#780000
0%
#790000
b10 ,
b101010101010100 -
0!
1%
#800000
0%
#810000
1!
1%
#820000
0%
#830000
b11 ,
b1010101010101000 -
0!
1%
#840000
0%
#850000
1!
1%
#860000
0%
#870000
b100 ,
b101010101010000 -
0!
1%
#880000
0%
#890000
1!
1%
#900000
0%
#910000
b101 ,
b1010101010100000 -
0!
1%
