Verilog Related Features/data_processing.v
module data_processing (
    input wire clk,
    input wire rst,
    input wire [15:0] adc_data,     // Входной код с АЦП
    input wire valid_in,            // Флаг: данные готовы
    output reg wr_en,               // Запись в FIFO разрешена
    output reg [15:0] result_data   // Результат обработки
);

  // Параметры масштабирования
  parameter SCALE = 1000;  // Масштаб в милливольтах
  parameter SHIFT = 16;    // Сдвиг вправо, аналог деления

  reg [31:0] scaled_temp;  // Временная переменная для расчёта

  always @(posedge clk or posedge rst) begin
    if (rst) begin
      result_data <= 0;
      wr_en <= 0;
      scaled_temp <= 0;
    end else begin
      if (valid_in) begin
        scaled_temp <= adc_data * SCALE;              // Умножаем
        result_data <= scaled_temp >> SHIFT;          // Сдвигаем
        wr_en <= 1;
      end else begin
        wr_en <= 0;
      end
    end
  end

endmodule

Verilog Related Features/data_processing_tb.v
`timescale 1ns / 1ps

module data_processing_tb;

  reg clk;
  reg rst;
  reg [15:0] adc_data;
  reg valid_in;
  wire wr_en;
  wire [15:0] result_data;

  // Instantiate the data_processing module
  data_processing uut (
    .clk(clk),
    .rst(rst),
    .adc_data(adc_data),
    .valid_in(valid_in),
    .wr_en(wr_en),
    .result_data(result_data)
  );

  // Clock generation (50 MHz)
  always #10 clk = ~clk;

  // VCD file for GTKWave
  initial begin
    $dumpfile("dump.vcd");
    $dumpvars(0, data_processing_tb);
  end

  initial begin
    // Initial values
    clk = 0;
    rst = 1;
    valid_in = 0;
    adc_data = 0;

    #40;
    rst = 0;

    // Test 1: adc_data = 0x0000 (0 V)
    @(posedge clk);
    adc_data = 16'h0000;
    valid_in = 1;
    @(posedge clk);
    valid_in = 0;

    // Test 2: adc_data = 0x4000 (≈ 0.4 V)
    repeat (2) @(posedge clk);
    adc_data = 16'h4000;
    valid_in = 1;
    @(posedge clk);
    valid_in = 0;

    // Test 3: adc_data = 0x8000 (≈ 0.8 V)
    repeat (2) @(posedge clk);
    adc_data = 16'h8000;
    valid_in = 1;
    @(posedge clk);
    valid_in = 0;

    // Test 4: adc_data = 0xC000 (≈ 1.2 V)
    repeat (2) @(posedge clk);
    adc_data = 16'hC000;
    valid_in = 1;
    @(posedge clk);
    valid_in = 0;

    // Test 5: adc_data = 0xFFFF (≈ 1.6 V)
    repeat (2) @(posedge clk);
    adc_data = 16'hFFFF;
    valid_in = 1;
    @(posedge clk);
    valid_in = 0;

    // End simulation
    #100;
    $finish;
  end

endmodule

Verilog Related Features/dump.vcd
$date
	Wed Apr 23 22:36:47 2025
$end
$version
	Icarus Verilog
$end
$timescale
	1ps
$end
$scope module data_processing_tb $end
$var wire 1 ! wr_en $end
$var wire 16 " result_data [15:0] $end
$var reg 16 # adc_data [15:0] $end
$var reg 1 $ clk $end
$var reg 1 % rst $end
$var reg 1 & valid_in $end
$scope module uut $end
$var wire 16 ' adc_data [15:0] $end
$var wire 1 $ clk $end
$var wire 1 % rst $end
$var wire 1 & valid_in $end
$var parameter 32 ( SCALE $end
$var parameter 32 ) SHIFT $end
$var reg 16 * result_data [15:0] $end
$var reg 32 + scaled_temp [31:0] $end
$var reg 1 ! wr_en $end
$upscope $end
$upscope $end
$enddefinitions $end
$comment Show the parameter values. $end
$dumpall
b10000 )
b1111101000 (
$end
#0
$dumpvars
b0 +
b0 *
b0 '
0&
1%
0$
b0 #
b0 "
0!
$end
#10000
1$
#20000
0$
#30000
1$
#40000
0$
0%
#50000
1!
1&
1$
#60000
0$
#70000
0!
0&
1$
#80000
0$
#90000
1$
#100000
0$
#110000
1!
b111110100000000000000000 +
1&
b100000000000000 #
b100000000000000 '
1$
#120000
0$
#130000
0!
0&
1$
#140000
0$
#150000
1$
#160000
0$
#170000
1!
b11111010 "
b11111010 *
b1111101000000000000000000 +
1&
b1000000000000000 #
b1000000000000000 '
1$
#180000
0$
#190000
0!
0&
1$
#200000
0$
#210000
1$
#220000
0$
#230000
1!
b111110100 "
b111110100 *
b10111011100000000000000000 +
1&
b1100000000000000 #
b1100000000000000 '
1$
#240000
0$
#250000
0!
0&
1$
#260000
0$
#270000
1$
#280000
0$
#290000
1!
b1011101110 "
b1011101110 *
b11111001111111110000011000 +
1&
b1111111111111111 #
b1111111111111111 '
1$
#300000
0$
#310000
0!
0&
1$
