Verilog Related Features/fifo_16bit.v
module fifo_16bit(
    input         clk,       // системный тактовый сигнал
    input         rst,       // асинхронный сброс (active high)
    input         wr_en,     // сигнал разрешения записи
    input         rd_en,     // сигнал разрешения чтения
    input  [15:0] data_in,   // входные 16-битные данные
    output reg [15:0] data_out, // выходные 16-битные данные
    output        full,      // сигнал, что FIFO заполнен
    output        empty      // сигнал, что FIFO пуст
);

  // Параметры FIFO
  parameter DEPTH = 16;   // Глубина массива памяти FIFO
  parameter ADDR_WIDTH = 4; // поскольку 16 = 2^4

  // Определяем память FIFO (16 элементов по 12 бит)
  reg [15:0] mem [0:DEPTH-1];   // Массив для хранения 16 16-битных слов

  // Указатели для записи и чтения
  reg [ADDR_WIDTH-1:0] wr_ptr;    // Куда записывается слово
  reg [ADDR_WIDTH-1:0] rd_ptr;    // Откуда считывается

  // Счётчик количества элементов в FIFO
  reg [ADDR_WIDTH:0] count;

  // Генерация флагов full и empty на основе count
  assign full  = (count == DEPTH);
  assign empty = (count == 0);

  // Основной блок: управление записью и чтением из FIFO
  always @(posedge clk or posedge rst) begin
    if (rst) begin    // При активном сбросе все указатели и счётчик обнуляются
      wr_ptr   <= 0;
      rd_ptr   <= 0;
      count    <= 0;
      data_out <= 0;

    end else begin
      // Если одновременно включены и запись, и чтение,
      // то производится запись и чтение одновременно – счётчик остаётся неизменным.
      if (wr_en && !full && rd_en && !empty) begin
        mem[wr_ptr] <= data_in;
        data_out   <= mem[rd_ptr];
        wr_ptr     <= wr_ptr + 1;
        rd_ptr     <= rd_ptr + 1;
      end
      else if (wr_en && !full) begin    // Запись данных, если массив mem не полон, счётчик +
        mem[wr_ptr] <= data_in;
        wr_ptr     <= wr_ptr + 1;
        count      <= count + 1;
      end
      else if (rd_en && !empty) begin   // Считывание данных, если массив не пуст, счётчик -
        data_out   <= mem[rd_ptr];
        rd_ptr     <= rd_ptr + 1;
        count      <= count - 1;
      end
    end
  end

endmodule

Verilog Related Features/fifo_16bit_tb.v
`timescale 1ns / 1ps

module fifo_16bit_tb;
  reg         clk;
  reg         rst;
  reg         wr_en;
  reg         rd_en;
  reg  [15:0] data_in;
  wire [15:0] data_out;
  wire        full;
  wire        empty;

  // Экземпляр FIFO
  fifo_16bit uut (
    .clk(clk),
    .rst(rst),
    .wr_en(wr_en),
    .rd_en(rd_en),
    .data_in(data_in),
    .data_out(data_out),
    .full(full),
    .empty(empty)
  );

  // Генерация тактового сигнала: период 20 ns (50 MHz)
  always #10 clk = ~clk;

  // Запись изменений сигналов в VCD-файл для просмотра в GTKWave
  initial begin
    $dumpfile("fifo_dump.vcd");
    $dumpvars(0, fifo_16bit_tb);
  end

  // Основной тестовый сценарий
  initial begin
    // Инициализация сигналов
    clk = 0;
    rst = 1;
    wr_en = 0;
    rd_en = 0;
    data_in = 16'd0;
    
    #25;  // Небольшая задержка для сброса
    rst = 0;

    // Запись 4 значений в FIFO
    wr_en = 1;
    data_in = 16'd100;  // Первое значение
    #20;
    data_in = 16'd200;  // Второе значение
    #20;
    data_in = 16'd300;  // Третье значение
    #20;
    data_in = 16'd400;  // Четвертое значение
    #20;
    wr_en = 0;

    // Небольшая пауза перед чтением
    #40;

    // Чтение данных из FIFO
    rd_en = 1;
    #20;  // Считываем первое слово
    rd_en = 0;
    #20;
    rd_en = 1;
    #20;  // Считываем второе слово
    rd_en = 0;
    #20;
    rd_en = 1;
    #20;  // Считываем третье слово
    rd_en = 0;
    #20;
    rd_en = 1;
    #20;  // Считываем четвёртое слово
    rd_en = 0;

    // Завершение симуляции
    #50;
    $finish;
  end

  // Мониторинг сигналов для отладки
  initial begin
    $monitor("Time=%0t | rst=%b | wr_en=%b | rd_en=%b | data_in=%d | data_out=%d | full=%b | empty=%b",
              $time, rst, wr_en, rd_en, data_in, data_out, full, empty);
  end

endmodule

Verilog Related Features/fifo_dump.vcd
$date
	Thu May 15 15:32:04 2025
$end
$version
	Icarus Verilog
$end
$timescale
	1ps
$end
$scope module fifo_16bit_tb $end
$var wire 1 ! full $end
$var wire 1 " empty $end
$var wire 16 # data_out [15:0] $end
$var reg 1 $ clk $end
$var reg 16 % data_in [15:0] $end
$var reg 1 & rd_en $end
$var reg 1 ' rst $end
$var reg 1 ( wr_en $end
$scope module uut $end
$var wire 1 $ clk $end
$var wire 16 ) data_in [15:0] $end
$var wire 1 & rd_en $end
$var wire 1 ' rst $end
$var wire 1 ( wr_en $end
$var wire 1 ! full $end
$var wire 1 " empty $end
$var parameter 32 * ADDR_WIDTH $end
$var parameter 32 + DEPTH $end
$var reg 5 , count [4:0] $end
$var reg 16 - data_out [15:0] $end
$var reg 4 . rd_ptr [3:0] $end
$var reg 4 / wr_ptr [3:0] $end
$upscope $end
$upscope $end
$enddefinitions $end
$comment Show the parameter values. $end
$dumpall
b10000 +
b100 *
$end
#0
$dumpvars
b0 /
b0 .
b0 -
b0 ,
b0 )
0(
1'
0&
b0 %
0$
b0 #
1"
0!
$end
#10000
1$
#20000
0$
#25000
b1100100 %
b1100100 )
1(
0'
#30000
0"
b1 ,
b1 /
1$
#40000
0$
#45000
b11001000 %
b11001000 )
#50000
b10 ,
b10 /
1$
#60000
0$
#65000
b100101100 %
b100101100 )
#70000
b11 ,
b11 /
1$
#80000
0$
#85000
b110010000 %
b110010000 )
#90000
b100 ,
b100 /
1$
#100000
0$
#105000
0(
#110000
1$
#120000
0$
#130000
1$
#140000
0$
#145000
1&
#150000
b11 ,
b1 .
b1100100 #
b1100100 -
1$
#160000
0$
#165000
0&
#170000
1$
#180000
0$
#185000
1&
#190000
b10 ,
b10 .
b11001000 #
b11001000 -
1$
#200000
0$
#205000
0&
#210000
1$
#220000
0$
#225000
1&
#230000
b1 ,
b11 .
b100101100 #
b100101100 -
1$
#240000
0$
#245000
0&
#250000
1$
#260000
0$
#265000
1&
#270000
1"
b0 ,
b100 .
b110010000 #
b110010000 -
1$
#280000
0$
#285000
0&
